woocommerce_prefect_tasks/__init__.py
woocommerce_prefect_tasks/_version.py
woocommerce_prefect_tasks/api.py
woocommerce_prefect_tasks/aws/__init__.py
woocommerce_prefect_tasks/aws/s3_client.py
woocommerce_prefect_tasks/aws/s3_storage.py
woocommerce_prefect_tasks/aws/secretsmanager_client.py
woocommerce_prefect_tasks/aws/secretsmanager_storage.py
woocommerce_prefect_tasks/tasks/__init__.py
woocommerce_prefect_tasks/tasks/create.py
woocommerce_prefect_tasks/tasks/delete.py
woocommerce_prefect_tasks/tasks/get.py
woocommerce_prefect_tasks/tasks/options.py
woocommerce_prefect_tasks/tasks/update.py
woocommerce_prefect_tasks-0.0.7.dist-info/LICENSE
woocommerce_prefect_tasks-0.0.7.dist-info/METADATA
woocommerce_prefect_tasks-0.0.7.dist-info/WHEEL
woocommerce_prefect_tasks-0.0.7.dist-info/top_level.txt
woocommerce_prefect_tasks-0.0.7.dist-info/RECORD
